links_connect/__init__.py
links_connect/callbacks/__init__.py
links_connect/callbacks/_01_core/__init__.py
links_connect/callbacks/_02_chained/__init__.py
links_connect/callbacks/_03_logger/__init__.py
links_connect/callbacks/_04_decorator/__init__.py
links_connect/callbacks/_04_decorator/driver.py
links_connect/callbacks/_04_decorator/registry.py
links_connect/callbacks/_05_store/__init__.py
links_connect-1.1.3.dist-info/LICENSE
links_connect-1.1.3.dist-info/METADATA
links_connect-1.1.3.dist-info/WHEEL
links_connect-1.1.3.dist-info/top_level.txt
links_connect-1.1.3.dist-info/RECORD
